setup.py
smappPy/MT.py
smappPy/__init__.py
smappPy/collection_util.py
smappPy/cross_validation.py
smappPy/date.py
smappPy/entities.py
smappPy/file_util.py
smappPy/geo_tweet.py
smappPy/get_tweets.py
smappPy/hadestunnel.py
smappPy/image_util.py
smappPy/index_util.py
smappPy/iter_util.py
smappPy/json_util.py
smappPy/languages.py
smappPy/math_util.py
smappPy/oauth.py
smappPy/retweet.py
smappPy/smapp_collections.py
smappPy/smapp_logging.py
smappPy/stopwords.py
smappPy/store_tweets.py
smappPy/text_clean.py
smappPy/tweepy_error_handling.py
smappPy/tweepy_pool.py
smappPy/tweet_filter.py
smappPy/tweet_util.py
smappPy/twitteruser_util.py
smappPy/unicode_csv.py
smappPy/xml_util.py
smappPy.egg-info/PKG-INFO
smappPy.egg-info/SOURCES.txt
smappPy.egg-info/dependency_links.txt
smappPy.egg-info/top_level.txt
smappPy/facebook/__init__.py
smappPy/facebook/cursor.py
smappPy/facebook/posts.py
smappPy/networks/__init__.py
smappPy/networks/build_follower_network.py
smappPy/networks/build_retweet_network.py
smappPy/networks/utilities.py
smappPy/tools/__init__.py
smappPy/tools/bson_filter.py
smappPy/tools/extract_user_data.py
smappPy/tools/text_wrapper.py
smappPy/tools/tweet_importer.py
smappPy/tools/tweet_json2csv.py
smappPy/tools/user_RT_proportion.py
smappPy/topics/__init__.py
smappPy/topics/build_docs.py
smappPy/topics/build_models.py
smappPy/topics/clean_docs.py
smappPy/topics/dictionary_util.py
smappPy/topics/export_topics_text.py
smappPy/topics/topic_barcharts.py
smappPy/topics/utilities.py
smappPy/topics/visualization.py
smappPy/user_collection/__init__.py
smappPy/user_collection/build_friends_followers.py
smappPy/user_collection/build_user_collection.py
smappPy/user_collection/fetch_userdocs.py
smappPy/user_collection/format_userdocs.py
smappPy/user_collection/get_friends_followers.py
smappPy/user_collection/network_edges.py
smappPy/user_collection/populate_user_tweets.py
smappPy/user_collection/upload_userdocs.py
smappPy/user_collection/userdocs.py