Metadata-Version: 1.1
Name: smappPy
Version: 0.1.28
Summary: NYU SMaPP lab utility library
Home-page: http://smapp.nyu.edu
Author: NYU SMaPP
Author-email: smapp_programmer-group@nyu.edu
License: GPLv2
Platform: UNKNOWN
Requires: tweepy
Requires: bson
Requires: urllib
Requires: simplejson
Requires: matplotlib
